CHANGELOG.txt
MANIFEST.in
README.rst
setup.py
inupypi/__init__.py
inupypi/htpasswd
inupypi.egg-info/PKG-INFO
inupypi.egg-info/SOURCES.txt
inupypi.egg-info/dependency_links.txt
inupypi.egg-info/entry_points.txt
inupypi.egg-info/requires.txt
inupypi.egg-info/top_level.txt
inupypi/core/__init__.py
inupypi/core/bread.py
inupypi/core/exceptions.py
inupypi/core/info.py
inupypi/static/favicon.ico
inupypi/static/vendor/initializr/css/bootstrap-responsive.css
inupypi/static/vendor/initializr/css/bootstrap-responsive.min.css
inupypi/static/vendor/initializr/css/bootstrap.css
inupypi/static/vendor/initializr/css/bootstrap.min.css
inupypi/static/vendor/initializr/css/main.css
inupypi/static/vendor/initializr/img/glyphicons-halflings-white.png
inupypi/static/vendor/initializr/img/glyphicons-halflings.png
inupypi/static/vendor/initializr/js/main.js
inupypi/static/vendor/initializr/js/vendor/bootstrap.js
inupypi/static/vendor/initializr/js/vendor/bootstrap.min.js
inupypi/static/vendor/initializr/js/vendor/jquery-1.8.2.min.js
inupypi/static/vendor/initializr/js/vendor/modernizr-2.6.1-respond-1.1.0.min.js
inupypi/static/vendor/tablesorter/build.xml
inupypi/static/vendor/tablesorter/changelog
inupypi/static/vendor/tablesorter/jquery-latest.js
inupypi/static/vendor/tablesorter/jquery.metadata.js
inupypi/static/vendor/tablesorter/jquery.tablesorter.js
inupypi/static/vendor/tablesorter/jquery.tablesorter.min.js
inupypi/static/vendor/tablesorter/themes/blue/asc.gif
inupypi/static/vendor/tablesorter/themes/blue/bg.gif
inupypi/static/vendor/tablesorter/themes/blue/blue.zip
inupypi/static/vendor/tablesorter/themes/blue/desc.gif
inupypi/static/vendor/tablesorter/themes/blue/style.css
inupypi/static/vendor/tablesorter/themes/green/asc.png
inupypi/static/vendor/tablesorter/themes/green/bg.png
inupypi/static/vendor/tablesorter/themes/green/desc.png
inupypi/static/vendor/tablesorter/themes/green/green.zip
inupypi/static/vendor/tablesorter/themes/green/style.css
inupypi/templates/_themes/inupypi/404.html
inupypi/templates/_themes/inupypi/500.html
inupypi/templates/_themes/inupypi/about.html
inupypi/templates/_themes/inupypi/base.html
inupypi/templates/_themes/inupypi/index.html
