Metadata-Version: 1.0
Name: inupypi
Version: 0.3.3
Summary: A multiple repository PyPI server implementation
Home-page: https://github.com/hallaj/inupypi
Author: Muhammad Hallaj Subery
Author-email: hallajs@gmail.com
License: BSD
Platform: FreeBSD
Platform: Linux
